evictionsplit/__init__.py
evictionsplit/admin.py
evictionsplit/app_settings.py
evictionsplit/apps.py
evictionsplit/auth_hooks.py
evictionsplit/models.py
evictionsplit/urls.py
evictionsplit/views.py
evictionsplit/locale/en/LC_MESSAGES/django.mo
evictionsplit/locale/en/LC_MESSAGES/django.po
evictionsplit/migrations/0001_initial.py
evictionsplit/migrations/0002_eviction_auto_join_alter_clocking_end.py
evictionsplit/migrations/__init__.py
evictionsplit/static/evictionsplit/base.css
evictionsplit/templates/evictionsplit/base.html
evictionsplit/templates/evictionsplit/eviction.html
evictionsplit/templates/evictionsplit/index.html
evictionsplit/templates/evictionsplit/list.html
evictionsplit/templates/evictionsplit/management.html
evictionsplit/templates/evictionsplit/partial/menu.html
evictionsplit/templatetags/__init__.py
evictionsplit/templatetags/smooth_timedelta.py
evictionsplit/tests/__init__.py
evictionsplit/tests/test_clocking.py
evictionsplit/tests/test_eviction.py
evictionsplit-1.1.2.dist-info/licenses/LICENSE
evictionsplit-1.1.2.dist-info/WHEEL
evictionsplit-1.1.2.dist-info/METADATA
evictionsplit-1.1.2.dist-info/RECORD
