Metadata-Version: 2.4
Name: evictionsplit
Version: 1.1.2
Summary: Alliance Auth plugin to manage loot split in evictions
Author-email: T'rahk Rokym <trahk.rokym@gmail.com>
Requires-Python: >=3.9
Classifier: Environment :: Web Environment
Classifier: Framework :: Django
Classifier: Framework :: Django :: 4.0
Classifier: Framework :: Django :: 4.2
Classifier: Intended Audience :: Developers
Classifier: License :: OSI Approved :: MIT License
Classifier: Operating System :: OS Independent
Classifier: Programming Language :: Python
Classifier: Programming Language :: Python :: 3.9
Classifier: Programming Language :: Python :: 3.10
Classifier: Programming Language :: Python :: 3.11
Classifier: Programming Language :: Python :: 3.12
Classifier: Programming Language :: Python :: 3.13
Classifier: Topic :: Internet :: WWW/HTTP
Classifier: Topic :: Internet :: WWW/HTTP :: Dynamic Content
License-File: LICENSE
Requires-Dist: allianceauth>=4
Project-URL: Changelog, https://gitlab.com/r0kym/aa-evictionsplit/-/blob/main/CHANGELOG.md
Project-URL: Homepage, https://gitlab.com/r0kym/aa-evictionsplit
Project-URL: Source, https://gitlab.com/r0kym/aa-evictionsplit
Project-URL: Tracker, https://gitlab.com/r0kym/aa-evictionsplit/-plugin-/issues
